{
  "persons": [
    {
      "name": "Arto Hellas",
      "number": "040-123456",
      "id": 1
    },
    {
      "name": "Ada Lovelace",
      "number": "39-44-5323523",
      "id": 2
    },
    {
      "name": "Dan Abramov",
      "number": "12-43-234345",
      "id": 3
    },
    {
      "name": "Mick Jackson",
      "number": "033-222-123",
      "id": 6
    },
    {
      "name": "Joonas Uusnäkki",
      "number": "0442966342",
      "id": 7
    },
    {
      "name": "Aki Nyberg",
      "number": "040-5567893",
      "id": 8
    }
  ]
}